ahui/__init__.py
ahui/pyemail.py
ahui/pywechat.py
ahui-1.0.1.dist-info/LICENSE.txt
ahui-1.0.1.dist-info/METADATA
ahui-1.0.1.dist-info/WHEEL
ahui-1.0.1.dist-info/top_level.txt
ahui-1.0.1.dist-info/RECORD
